airflow_code_editor/VERSION
airflow_code_editor/__init__.py
airflow_code_editor/airflow_code_editor.py
airflow_code_editor/app_builder_view.py
airflow_code_editor/commons.py
airflow_code_editor/fastapi_app.py
airflow_code_editor/fs.py
airflow_code_editor/git.py
airflow_code_editor/presigned.py
airflow_code_editor/tree.py
airflow_code_editor/utils.py
airflow_code_editor/api/__init__.py
airflow_code_editor/api/api.py
airflow_code_editor/api/code_editor.yaml
airflow_code_editor/api/fastapi_endpoints.py
airflow_code_editor/api/flask_endpoints.py
airflow_code_editor/static/airflow_code_editor.js
airflow_code_editor/static/airflow_code_editor.js.map
airflow_code_editor/static/icon.png
airflow_code_editor/static/css/airflowDefaultTheme.css
airflow_code_editor/static/css/bootstrap.min.css
airflow_code_editor/static/css/brands.min.css
airflow_code_editor/static/css/codemirror.css
airflow_code_editor/static/css/editor_v2.css
airflow_code_editor/static/css/editor_v3.css
airflow_code_editor/static/css/fontawesome.min.css
airflow_code_editor/static/css/regular.min.css
airflow_code_editor/static/css/solid.min.css
airflow_code_editor/static/css/style.css
airflow_code_editor/static/css/v4-font-face.min.css
airflow_code_editor/static/css/vue-good-table.css
airflow_code_editor/static/css/vue-tree.css
airflow_code_editor/static/fonts/LICENSE
airflow_code_editor/static/fonts/material-icons.woff
airflow_code_editor/static/fonts/material-icons.woff2
airflow_code_editor/static/webfonts/fa-brands-400.ttf
airflow_code_editor/static/webfonts/fa-brands-400.woff2
airflow_code_editor/static/webfonts/fa-regular-400.ttf
airflow_code_editor/static/webfonts/fa-regular-400.woff2
airflow_code_editor/static/webfonts/fa-solid-900.ttf
airflow_code_editor/static/webfonts/fa-solid-900.woff2
airflow_code_editor/static/webfonts/fa-v4compatibility.ttf
airflow_code_editor/static/webfonts/fa-v4compatibility.woff2
airflow_code_editor/templates/__init__.py
airflow_code_editor/templates/index.html
airflow_code_editor-8.1.1.dist-info/LICENSE
airflow_code_editor-8.1.1.dist-info/METADATA
airflow_code_editor-8.1.1.dist-info/WHEEL
airflow_code_editor-8.1.1.dist-info/entry_points.txt
airflow_code_editor-8.1.1.dist-info/top_level.txt
airflow_code_editor-8.1.1.dist-info/RECORD
