Metadata-Version: 2.1
Name: airflow-code-editor
Version: 8.1.1
Summary: Apache Airflow code editor and file manager
Home-page: https://github.com/andreax79/airflow-code-editor
Author: Andrea Bonomi
Author-email: andrea.bonomi@gmail.com
License: Apache License 2.0
Project-URL: Bug Tracker, http://github.com/andreax79/airflow-code-editor/issues
Project-URL: Source Code, http://github.com/andreax79/airflow-code-editor
Keywords: airflow,airflow-plugin,apache-airflow,editor
Platform: any
Classifier: Development Status :: 5 - Production/Stable
Classifier: Environment :: Web Environment
Classifier: Intended Audience :: Developers
Classifier: Intended Audience :: System Administrators
Classifier: License :: OSI Approved :: Apache Software License
Classifier: Operating System :: OS Independent
Classifier: Programming Language :: Python
Classifier: Topic :: System :: Monitoring
Classifier: Framework :: Apache Airflow
Classifier: Programming Language :: Python :: 3.6
Classifier: Programming Language :: Python :: 3.7
Classifier: Programming Language :: Python :: 3.8
Classifier: Programming Language :: Python :: 3.9
Classifier: Programming Language :: Python :: 3.10
Classifier: Programming Language :: Python :: 3.11
Classifier: Programming Language :: Python :: 3.12
Classifier: Programming Language :: Python :: 3.13
Requires-Python: >=3.6
License-File: LICENSE
Requires-Dist: apache-airflow
Requires-Dist: fs>=2.4.16
Requires-Dist: pss>=1.44
Provides-Extra: test
Requires-Dist: pytest; extra == "test"
